my_test_hello_library-0.3.dist-info/DESCRIPTION.rst
my_test_hello_library-0.3.dist-info/METADATA
my_test_hello_library-0.3.dist-info/RECORD
my_test_hello_library-0.3.dist-info/WHEEL
my_test_hello_library-0.3.dist-info/metadata.json
my_test_hello_library-0.3.dist-info/top_level.txt
mytesthellolibrary/__init__.py
mytesthellolibrary/helloworld.py
