Metadata-Version: 2.0
Name: my-test-hello-library
Version: 0.3
Summary: sum two numbers
Home-page: https://github.com/sebasgverde/mytesthellolibrary
Author: Sebastian Garcia Valencia
Author-email: sebasgverde@gmail.com
License: MIT
Platform: UNKNOWN
Requires-Python: >=2.7
